Workbook

Sheet How to use
B2: Withholding tax
B3: User acceptance test
B4: A sign-off for doctor withholding tax, including split payments, doctor balance, and the doctor payment reports.
B6: What you are checking
B7: This pack checks doctor withholding tax on channeling, and the reports that changed because a payment can now be split. There are two different percentages. The percentage on the doctor is how many of the selected bookings are paid with tax. The percent on the payment screen, next to Apply All WHT, is the tax rate taken off those bookings. It is not the same number. Tick Apply All WHT and the whole payment is one taxed receipt. Leave it off and the doctor percentage decides. Earliest bookings are taxed first. If that rounds to none of them, or to all of them, there is still only one receipt. Otherwise there are two: a WHT receipt and a normal doctor-payment receipt. Only the bookings without tax move to a hidden session. The doctor balance falls by the full fee of both receipts. The cash that leaves the till is the net. The tax is not left on the doctor. It shows on the Withholding Tax Report. DPAY has its own balance and is not changed by this payment.
B14: How to fill this in
B15: 1 Use the UAT address and the login you were given. You need a cashier with an open shift and enough till, and someone who can open Reports.
B16: 2 On How to use, replace the sample figures with the payment you are about to make. Use those results when you check the till, the balance, and the reports.
B17: 3 On Test Cases, do the sections in order. Each case says what to set up. Write the rate from the payment screen in the Notes of WHT-07.
B18: 4 Type only in the yellow cells. On Test Cases that is Result and Notes. On Sign-off that is your name, date, environment, and comments.
B19: 5 Result must be Pass, Fail, Blocked, or Not run. Use the dropdown. If you choose Fail or Blocked, write what you saw in Notes.
B20: 6 Open Sign-off when you finish. The counts and the overall result calculate themselves. Do not type over them.
B22: What the colours mean
B23: Look | C23: Meaning
B24: Yellow cell, blue text | C24: Type here. Result, Notes, and the Sign-off details.
B25: Shaded row | C25: A test case. Do not type in the white or blue text.
B26: Pass | C26: It matched the expected result.
B27: Fail | C27: It did not. Write what you saw in Notes.
B28: Blocked | C28: You could not run it. Write why in Notes.
B29: Not run | C29: Left blank, or not started.
B31: Example of a filled result · this is not a real test
B32: ID | C32: Test | D32: Result | E32: Notes
B33: WHT-00 | C33: Example only — do not test this row | D33: Pass | E33: Both slips printed. The balance fell by the full fee.
B35: Before you start, UAT should have two doctors, unpaid bookings on at least two days and two branches, a till with cash, card, slip, cheque, and e-wallet, and permission for Doctor Payments, Doctor Balance, Consultant Payments, Withholding Tax, and DPAY Doctor Balance. Receipt numbers use the branch code, then CHANN-DOC-WHT/, CHANN-DOC-PAY/, CHANN-DOC-WHT-REF/, or CHANN-DOC-REF/.
B37: Work out this payment before you run it
B38: Type the yellow figures from the screen. The results update themselves. The sample numbers are only an example — replace them with the payment you are checking. Percentages are typed as 50 for 50%.
B40: Bookings you will pay | C40: 10 | D40: How many bookings are selected.
B41: Doctor WHT percentage | C41: 50 | D41: The percentage on the doctor, not the tax rate.
B42: Tax rate on the payment screen | C42: 5 | D42: The percent next to Apply All WHT. Type 0 if the tick is off and the doctor percentage rounds to no bookings.
B43: Fee of the taxed bookings | C43: 6000 | D43: When every booking is taxed, put the whole fee here and 0 below. When none are taxed, put 0 here.
B44: Fee of the other bookings | C44: 4000 | D44: When none are taxed, put the whole fee here.
B46: Result | C46: Value | D46: What to expect
B47: Bookings with tax | C47: =MIN(C40,MAX(0,ROUND(C40*C41/100,0))) | D47: Earliest bookings: session date, then start time, then appointment number.
B48: Bookings without tax | C48: =C40-C47 | D48: These are the ones that move to the hidden session, when there are two receipts.
B49: Receipts | C49: =IF(OR(C47<=0,C47>=C40),1,2) | D49: One receipt when none or all of the bookings are taxed. Two when the set is split.
B50: Tax withheld | C50: =IF(C47<=0,0,ROUND(C43*C42/100,0)) | D50: Taken only from the taxed bookings, at the rate on the screen.
B51: Cash leaving the till | C51: =IF(C47<=0,C44,IF(C47>=C40,C43-C50,C43-C50+C44)) | D51: Taxed fees minus tax, plus the other fees. This is the net, not the full fee.
B52: Doctor balance falls by | C52: =IF(C47<=0,C44,IF(C47>=C40,C43,C43+C44)) | D52: The full fee of both receipts. The tax is not left on the doctor.

Sheet Test Cases
A1: Withholding tax · test cases
A2: Do the sections in order. Yellow cells only: choose a Result, and write Notes when something fails, when you are blocked, or when a case asks you to record a figure. Use How to use to work out the tax, the cash, and the balance before you pay.
A4: ID | B4: Area | C4: Who | D4: Test | E4: Steps | F4: Expected result | G4: Result | H4: Notes
A5: A | D5: A. Doctor percentage
A6: WHT-01 | B6: Doctor percentage | C6: Cashier | D6: Save a doctor percentage | E6: 1. Open the doctor. 2. Set WHT percentage to 50 and save. 3. Open the doctor again. | F6: 50 is saved and still shows. The note on the field says this is the share of bookings paid with tax, and that 0 does not split.
A7: WHT-02 | B7: Doctor percentage | C7: Cashier | D7: Change it, and reject a bad value | E7: 1. Change the percentage and save. 2. Try a number below 0, and a number above 100. 3. Clear the field and save. | F7: A valid change is saved. Below 0 and above 100 are rejected and not saved. A blank field saves as 0.
A8: WHT-03 | B8: Doctor percentage | C8: Cashier | D8: Two doctors, and an old payment | E8: 1. Give a second doctor a different percentage. 2. Pay the first doctor, then change that doctor's percentage. 3. Open the payment you already made. | F8: Each doctor keeps their own percentage. Changing it later does not change a payment already made.
A9: B | D9: B. How a payment splits
A10: WHT-04 | B10: Payment | C10: Cashier | D10: No percentage | E10: 1. Set the doctor to 0%. 2. Leave Apply All WHT unticked. 3. Pay several bookings that have a fee. | F10: One receipt. No tax. Bookings stay on their session. Nothing moves to a hidden session. The receipt number is the normal doctor-payment series.
A11: WHT-05 | B11: Payment | C11: Cashier | D11: Every booking taxed | E11: 1. Set the doctor to 100%. 2. Leave Apply All WHT unticked. 3. Pay several bookings. | F11: One receipt, with tax on the full fee. No second receipt. Bookings stay on their session.
A12: WHT-06 | B12: Payment | C12: Cashier | D12: Apply All WHT | E12: 1. Leave the doctor percentage below 100, for example 50. 2. Tick Apply All WHT. 3. Pay several bookings. | F12: One receipt, with tax on the full fee, even though the doctor percentage is lower. Bookings stay on their session. There is no hidden session.
A13: WHT-07 | B13: Payment | C13: Cashier | D13: Tax rate on screen is zero | E13: 1. Open Make doctor payment. 2. Read the percent next to Apply All WHT. | F13: If that percent is 0, the tick cannot be turned on and no tax is deducted. If it shows a rate, use that rate for the tax checks below. Write the rate in Notes.
A14: WHT-08 | B14: Payment | C14: Cashier | D14: Different percentages | E14: 1. Use the worked example on How to use, and replace the sample numbers. 2. Pay each of these, with Apply All WHT off, on bookings that all have a fee: 10 bookings at 50%, 10 at 30%, 3 at 50%, 2 at 25%, 1 at 50%, 1 at 40%. 3. You can reuse the same doctor and change the percentage between payments. Use fresh unpaid bookings each time. | F14: 10 at 50% is 5 taxed and 5 not. 10 at 30% is 3 and 7. 3 at 50% is 2 and 1. 2 at 25% is 1 and 1. 1 at 50% is one taxed receipt and nothing moves. 1 at 40% is one receipt with no tax. The earliest bookings are the taxed ones: session date, then start time, then appointment number. Paying only some bookings uses that smaller count, not the whole session.
A15: WHT-09 | B15: Payment | C15: Cashier | D15: Confirm screen, tax, and the till | E15: 1. On a split, read the confirm screen before you pay. 2. Note the till for that payment method. 3. Pay, then read the till again. | F15: The screen shows the taxed count, the other count, the tax, and the net. Tax is the screen rate on the taxed bookings only, not on the whole payment. The till falls by the net: taxed fees minus tax, plus the other fees. It does not fall by the full fee.
A16: WHT-10 | B16: Payment | C16: Cashier | D16: Payment methods, and a payment that must not save | E16: 1. Complete a split in cash, then card, slip, cheque, and e-wallet. Use a fresh set of bookings each time. 2. Try a card, slip, or e-wallet with the reference left empty. 3. Try a payment with no open shift, and one where the till does not have enough of that method. 4. Include a booking whose professional fee is already zero or fully refunded, so one side of the split has nothing to pay. | F16: Each method completes and the reference is stored on both receipts. A missing reference is refused. No shift, or not enough till, saves nothing: no receipt, no balance change, no hidden session. A side with nothing to pay is refused and nothing is saved.
A17: C | D17: C. Two receipts
A18: WHT-11 | B18: Receipts | C18: Cashier | D18: Both receipts, and the numbers | E18: 1. Note the last doctor-payment number and the last WHT number, if you have one. 2. Make a split. 3. Make another split, then one normal channel receipt, then a doctor payment with no tax. | F18: The split creates both receipts together. The taxed one is {branch}CHANN-DOC-WHT/ and the other is {branch}CHANN-DOC-PAY/, each 8 digits. The next payment continues its own series. The two series do not reuse or skip each other's numbers. A channel receipt stays on CHANN/ and is not affected. If a payment fails, neither receipt of that pair exists.
A19: WHT-12 | B19: Receipts | C19: Cashier | D19: Print both slips | E19: 1. Print from the payment you just made. 2. Reprint from Doctor Payments. 3. Reprint from Receipt Manager. | F19: Two slips. The WHT slip is first. Doctor, patients, fees, tax, and net match the confirm screen. Nothing is cut off or overlapping. Reprint shows the same two slips.
A20: D | D20: D. Hidden session
A21: WHT-13 | B21: Hidden session | C21: Cashier | D21: Only the untaxed bookings move | E21: 1. After a split, open the original session. 2. Look for the taxed bookings and the others. 3. Open Channeling and the normal session list for that doctor and day. 4. Try to edit the hidden session. | F21: Taxed bookings are still on the original session. The others have left it. Their appointment numbers are unchanged. The hidden session does not appear in the normal session list or on the channel desk. It cannot be edited.
A22: WHT-14 | B22: Hidden session | C22: Cashier | D22: One hidden session per day and branch | E22: 1. Make a second split for the same doctor, branch, and day. 2. Make one for a different day, and one for a different branch. 3. Try a payment where two selected bookings share an appointment number on that day and branch. 4. Try one whose appointment number is already on that day's hidden session. | F22: The same doctor, branch, and day share one hidden session. A different day or branch gets its own. A repeated appointment number is refused with a clear message, and nothing is saved: no receipts, no balance change.
A23: E | D23: E. Cancel
A24: WHT-15 | B24: Cancel | C24: Cashier | D24: Cancel the pair | E24: 1. With no shift, try to cancel. 2. Try with an empty reason. 3. Open a shift, cancel from the WHT receipt, then on a new pair cancel from the other receipt. | F24: No shift, or no reason, does not cancel. Cancel from either receipt cancels both. The WHT cancel number is {branch}CHANN-DOC-WHT-REF/ and the other is {branch}CHANN-DOC-REF/. Each series continues on its own and does not reuse a payment number. Both originals show as canceled and cannot be canceled again.
A25: WHT-16 | B25: Cancel | C25: Cashier | D25: Bookings come back | E25: 1. After cancel, open the original session and try to pay the same bookings again. 2. On another payment, give the original session a new booking with the same appointment number, then try to cancel. | F25: Bookings are unpaid and can be paid again. Moved bookings are back on the original session with the same appointment number. If that number is now taken, cancel is refused and the payment, receipts, balance, and hidden session stay as they were.
A26: WHT-17 | B26: Cancel | C26: Cashier | D26: Cancel a payment that was one receipt | E26: 1. Cancel a 0% payment, a 100% payment, and an Apply All payment. | F26: Each creates one cancel receipt only. A 0% payment uses the normal cancel series. A taxed one uses the WHT cancel series. No hidden session is involved.
A27: F | D27: F. Doctor balance
A28: WHT-18 | B28: Doctor balance | C28: Accounts | D28: Balance before you pay | E28: 1. Open the doctor and note Current cash balance. 2. Open Reports → Doctor Balance for this doctor, as of today. 3. Open the linked account statement. | F28: The doctor record and Doctor Balance Report show the same figure. Write it in Notes. This is the channeling balance. It is not the DPAY balance.
A29: WHT-19 | B29: Doctor balance | C29: Accounts | D29: Balance after a split | E29: 1. Note the balance, and note a second doctor's balance. 2. Make a split. Use the worked example so you know the full fee and the cash paid. 3. Open the doctor, Doctor Balance as of today, and the second doctor. | F29: The balance falls by the full fee of both receipts added together, not by the cash the doctor received. Use the worked example on How to use: the doctor balance falls by that sheet's 'Doctor balance falls by', and the till falls by 'Cash leaving the till'. The tax is not still owed to the doctor. The sample on that sheet (fees 6,000 and 4,000, tax rate 5%) falls by 10,000 and the till by 9,700 — only when those are the figures you typed. The other doctor's balance does not change. Write the before and after figures in Notes.
A30: WHT-20 | B30: Doctor balance | C30: Accounts | D30: As-of date and the statement | E30: 1. Run Doctor Balance as of yesterday, then as of today. 2. Open the doctor's account statement and find the payment. | F30: Yesterday does not include today's payment. Today does. The statement shows one line for each receipt. Each line reduces the balance by that receipt's full fee, not by the cash paid on that slip.
A31: WHT-21 | B31: Doctor balance | C31: Accounts | D31: Balance after cancel | E31: 1. Cancel the split you measured. 2. Open the doctor, Doctor Balance as of today, and the account statement. | F31: The balance returns to the figure you wrote down before the payment. The statement shows the reversal of both receipts. Neither half of the split is left on the balance.
A32: WHT-22 | B32: Doctor balance | C32: Accounts | D32: Channeling and DPAY stay apart | E32: 1. Note Doctor Balance and DPAY Doctor Balance for the same doctor. 2. Make a channeling split. 3. Separately, make a DPAY doctor payment for that doctor. | F32: The channeling payment changes Doctor Balance and does not change DPAY Doctor Balance. The DPAY payment changes DPAY Doctor Balance and does not change the channeling balance on the doctor record.
A33: G | D33: G. Doctor payment reports
A34: WHT-23 | B34: Payment reports | C34: Accounts | D34: Consultant Payments after a split | E34: 1. Open Reports → Consultant Payments. 2. Use the session dates of the bookings, not only the payment date. 3. Find the bookings you just paid. | F34: One row per booking. Taxed bookings show the CHANN-DOC-WHT receipt. Their tax shares add up to the tax on that receipt. The other bookings show the CHANN-DOC-PAY receipt and zero tax. Net is the fee minus the discount minus that row's tax. Status is Paid. Bookings that moved to the hidden session still appear, on the original session time.
A35: WHT-24 | B35: Payment reports | C35: Accounts | D35: Filters, print, and export | E35: 1. Filter to Paid, then to Due Pay. 2. Filter to this doctor, then to another doctor. 3. Print, and export Excel. | F35: Paid shows both halves of the split. Due Pay hides them. This doctor does not show the other doctor's bookings. Print and Excel include both receipt numbers and the tax, and the totals match the screen.
A36: WHT-25 | B36: Payment reports | C36: Accounts | D36: Consultant Payments after cancel | E36: 1. Cancel the split. 2. Run Consultant Payments again for the same session dates. | F36: Those bookings are Due Pay. The receipt number, tax, net adjustment, paid date, and paid-by are clear. They can be paid again, and a new payment shows the new receipt.
A37: WHT-26 | B37: Payment reports | C37: Accounts | D37: Withholding Tax Report | E37: 1. Open Reports → Withholding Tax, detail, for the payment date. 2. Find the split, then a 0% payment, then an Apply All or 100% payment. 3. Filter to this doctor. | F37: The WHT receipt appears once. The other receipt of the split does not. Amount, tax percent, tax, and net match the slip. A 0% payment does not appear. Apply All and 100% appear as one line for the whole fee. Another doctor's tax is not in this doctor's filter.
A38: WHT-27 | B38: Payment reports | C38: Accounts | D38: Withholding tax after cancel, and the summary | E38: 1. Note the tax total for the period. 2. Cancel the WHT receipt's payment. 3. Run the detail again, then the summary. | F38: The cancel appears as its own reversing line on the CHANN-DOC-WHT-REF receipt, and the tax total for the period goes back. Summary groups by doctor and tax percent, and its tax matches the detail.
A39: WHT-28 | B39: Payment reports | C39: Accounts | D39: Cashier summary | E39: 1. Open the cashier summary for the shift in which you made a split. 2. Find the doctor-payment lines. | F39: Both receipts are listed. The cash that left the till is the net, not the full fee. It matches the till movement you noted on the payment.

Sheet Sign-off
A1: Sign-off
A2: Counts and the overall result come from the Test Cases sheet. Type only in the yellow cells.
A4: Tester | D4: Overall result
A5: Name | D5: Result | E5: =IF(D12>0,"Not accepted",IF(F12>0,"Incomplete",IF(E12>0,"Accepted with blockers","Accepted")))
A6: Role | D6: Pass rate | E6: =IF(B12=0,"—",C12/B12)
A7: Date tested | D7: Accepted — every case is Pass. Accepted with blockers — no failures, but at least one case is Blocked. Incomplete — at least one case is still blank or Not run. Not accepted — at least one case is Fail.
A8: Environment / URL
A9: Version or build, if you have it
A11: Cases | B11: Total | C11: Passed | D11: Failed | E11: Blocked | F11: Not run
A12: All cases | B12: =COUNTIF('Test Cases'!$A$5:$A$39,"*-*") | C12: =COUNTIFS('Test Cases'!$A$5:$A$39,"*-*",'Test Cases'!$G$5:$G$39,"Pass") | D12: =COUNTIFS('Test Cases'!$A$5:$A$39,"*-*",'Test Cases'!$G$5:$G$39,"Fail") | E12: =COUNTIFS('Test Cases'!$A$5:$A$39,"*-*",'Test Cases'!$G$5:$G$39,"Blocked") | F12: =B12-C12-D12-E12
A14: By area
A15: Area | B15: Cases | C15: Passed | D15: Failed | E15: Blocked | F15: Not run
A16: Doctor percentage | B16: =COUNTIFS('Test Cases'!$A$5:$A$39,"*-*",'Test Cases'!$B$5:$B$39,A16) | C16: =COUNTIFS('Test Cases'!$A$5:$A$39,"*-*",'Test Cases'!$B$5:$B$39,A16,'Test Cases'!$G$5:$G$39,"Pass") | D16: =COUNTIFS('Test Cases'!$A$5:$A$39,"*-*",'Test Cases'!$B$5:$B$39,A16,'Test Cases'!$G$5:$G$39,"Fail") | E16: =COUNTIFS('Test Cases'!$A$5:$A$39,"*-*",'Test Cases'!$B$5:$B$39,A16,'Test Cases'!$G$5:$G$39,"Blocked") | F16: =B16-C16-D16-E16
A17: Payment | B17: =COUNTIFS('Test Cases'!$A$5:$A$39,"*-*",'Test Cases'!$B$5:$B$39,A17) | C17: =COUNTIFS('Test Cases'!$A$5:$A$39,"*-*",'Test Cases'!$B$5:$B$39,A17,'Test Cases'!$G$5:$G$39,"Pass") | D17: =COUNTIFS('Test Cases'!$A$5:$A$39,"*-*",'Test Cases'!$B$5:$B$39,A17,'Test Cases'!$G$5:$G$39,"Fail") | E17: =COUNTIFS('Test Cases'!$A$5:$A$39,"*-*",'Test Cases'!$B$5:$B$39,A17,'Test Cases'!$G$5:$G$39,"Blocked") | F17: =B17-C17-D17-E17
A18: Receipts | B18: =COUNTIFS('Test Cases'!$A$5:$A$39,"*-*",'Test Cases'!$B$5:$B$39,A18) | C18: =COUNTIFS('Test Cases'!$A$5:$A$39,"*-*",'Test Cases'!$B$5:$B$39,A18,'Test Cases'!$G$5:$G$39,"Pass") | D18: =COUNTIFS('Test Cases'!$A$5:$A$39,"*-*",'Test Cases'!$B$5:$B$39,A18,'Test Cases'!$G$5:$G$39,"Fail") | E18: =COUNTIFS('Test Cases'!$A$5:$A$39,"*-*",'Test Cases'!$B$5:$B$39,A18,'Test Cases'!$G$5:$G$39,"Blocked") | F18: =B18-C18-D18-E18
A19: Hidden session | B19: =COUNTIFS('Test Cases'!$A$5:$A$39,"*-*",'Test Cases'!$B$5:$B$39,A19) | C19: =COUNTIFS('Test Cases'!$A$5:$A$39,"*-*",'Test Cases'!$B$5:$B$39,A19,'Test Cases'!$G$5:$G$39,"Pass") | D19: =COUNTIFS('Test Cases'!$A$5:$A$39,"*-*",'Test Cases'!$B$5:$B$39,A19,'Test Cases'!$G$5:$G$39,"Fail") | E19: =COUNTIFS('Test Cases'!$A$5:$A$39,"*-*",'Test Cases'!$B$5:$B$39,A19,'Test Cases'!$G$5:$G$39,"Blocked") | F19: =B19-C19-D19-E19
A20: Cancel | B20: =COUNTIFS('Test Cases'!$A$5:$A$39,"*-*",'Test Cases'!$B$5:$B$39,A20) | C20: =COUNTIFS('Test Cases'!$A$5:$A$39,"*-*",'Test Cases'!$B$5:$B$39,A20,'Test Cases'!$G$5:$G$39,"Pass") | D20: =COUNTIFS('Test Cases'!$A$5:$A$39,"*-*",'Test Cases'!$B$5:$B$39,A20,'Test Cases'!$G$5:$G$39,"Fail") | E20: =COUNTIFS('Test Cases'!$A$5:$A$39,"*-*",'Test Cases'!$B$5:$B$39,A20,'Test Cases'!$G$5:$G$39,"Blocked") | F20: =B20-C20-D20-E20
A21: Doctor balance | B21: =COUNTIFS('Test Cases'!$A$5:$A$39,"*-*",'Test Cases'!$B$5:$B$39,A21) | C21: =COUNTIFS('Test Cases'!$A$5:$A$39,"*-*",'Test Cases'!$B$5:$B$39,A21,'Test Cases'!$G$5:$G$39,"Pass") | D21: =COUNTIFS('Test Cases'!$A$5:$A$39,"*-*",'Test Cases'!$B$5:$B$39,A21,'Test Cases'!$G$5:$G$39,"Fail") | E21: =COUNTIFS('Test Cases'!$A$5:$A$39,"*-*",'Test Cases'!$B$5:$B$39,A21,'Test Cases'!$G$5:$G$39,"Blocked") | F21: =B21-C21-D21-E21
A22: Payment reports | B22: =COUNTIFS('Test Cases'!$A$5:$A$39,"*-*",'Test Cases'!$B$5:$B$39,A22) | C22: =COUNTIFS('Test Cases'!$A$5:$A$39,"*-*",'Test Cases'!$B$5:$B$39,A22,'Test Cases'!$G$5:$G$39,"Pass") | D22: =COUNTIFS('Test Cases'!$A$5:$A$39,"*-*",'Test Cases'!$B$5:$B$39,A22,'Test Cases'!$G$5:$G$39,"Fail") | E22: =COUNTIFS('Test Cases'!$A$5:$A$39,"*-*",'Test Cases'!$B$5:$B$39,A22,'Test Cases'!$G$5:$G$39,"Blocked") | F22: =B22-C22-D22-E22
A23: Total | B23: =SUM(B16:B22) | C23: =SUM(C16:C22) | D23: =SUM(D16:D22) | E23: =SUM(E16:E22) | F23: =SUM(F16:F22) | G23: =IF(B23=B12,"Totals match","Check the area totals")
A25: Comments
A31: Sign-off
B32: Name | D32: Signature | F32: Date
A33: Tester
A34: Reviewer
A36: Not run includes any case left blank. Area totals should match the Total row above. A split payment is two receipts, but the doctor balance moves by the full fee of both. The tax is reported on its own.

Sheet Lists
A1: Pass
A2: Fail
A3: Blocked
A4: Not run
